{
  "bio": [
    "привет, я мари.",
    "давай снимем кадры, в которых ты настоящая.",
    "живые, честные, твои.",
    "",
    "живу в москве,",
    "но часто меня можно поймать в других странах."
  ],
  "links": [
    { "label": "Instagram",              "url": "https://www.instagram.com/miinaeva/",    "external": true },
    { "label": "YouTube",                "url": "https://www.youtube.com/@marieminaeva",  "external": true },
    { "label": "minaevamarie@gmail.com", "url": "mailto:minaevamarie@gmail.com",          "external": false }
  ]
}
